{
  "kind": "singleType",
  "collectionName": "aboutpages",
  "info": {
    "singularName": "aboutpage",
    "pluralName": "aboutpages",
    "displayName": "aboutpage"
  },
  "options": {
    "draftAndPublish": true
  },
  "pluginOptions": {
    "i18n": {
      "localized": true
    }
  },
  "attributes": {
    "img": {
      "type": "media",
      "pluginOptions": {
        "i18n": {
          "localized": true
        }
      },
      "multiple": false,
      "allowedTypes": [
        "images",
        "files",
        "videos",
        "audios"
      ]
    },
    "imgurl": {
      "type": "string",
      "pluginOptions": {
        "i18n": {
          "localized": true
        }
      }
    },
    "title": {
      "type": "string",
      "pluginOptions": {
        "i18n": {
          "localized": true
        }
      }
    },
    "desc": {
      "type": "text",
      "pluginOptions": {
        "i18n": {
          "localized": true
        }
      }
    },
    "worksection": {
      "type": "component",
      "pluginOptions": {
        "i18n": {
          "localized": true
        }
      },
      "component": "home.work-section",
      "repeatable": false
    },
    "Teams": {
      "type": "component",
      "pluginOptions": {
        "i18n": {
          "localized": true
        }
      },
      "component": "home.team",
      "repeatable": false
    },
    "achievement": {
      "type": "component",
      "pluginOptions": {
        "i18n": {
          "localized": true
        }
      },
      "component": "home.achievements",
      "repeatable": false
    },
    "contact": {
      "type": "component",
      "pluginOptions": {
        "i18n": {
          "localized": true
        }
      },
      "component": "home.contact",
      "repeatable": true
    },
    "footer": {
      "type": "component",
      "pluginOptions": {
        "i18n": {
          "localized": true
        }
      },
      "component": "home.foot",
      "repeatable": false
    },
    "teamsprofessional": {
      "type": "component",
      "pluginOptions": {
        "i18n": {
          "localized": true
        }
      },
      "component": "home.teams-professionals",
      "repeatable": false
    }
  }
}
